the37lab_ampa_sdk/__init__.py
the37lab_ampa_sdk/client.py
the37lab_ampa_sdk-0.1.1769779164.dist-info/METADATA
the37lab_ampa_sdk-0.1.1769779164.dist-info/WHEEL
the37lab_ampa_sdk-0.1.1769779164.dist-info/top_level.txt
the37lab_ampa_sdk-0.1.1769779164.dist-info/RECORD
