Metadata-Version: 2.4
Name: the37lab_ampa_sdk
Version: 0.1.1769779164
Summary: Python SDK for the AMPA API
Author-email: the37lab <info@the37lab.com>
Classifier: Programming Language :: Python :: 3
Classifier: License :: Other/Proprietary License
Classifier: Operating System :: OS Independent
Requires-Python: >=3.9
Requires-Dist: requests
